gt_sat_infile_api/__init__.py
gt_sat_infile_api/conection.py
gt_sat_infile_api/login.py
gt_sat_infile_api/parser.py
src/__init__.py
src/example.py
gt_sat_infile_api-1.2.1.dist-info/METADATA
gt_sat_infile_api-1.2.1.dist-info/WHEEL
gt_sat_infile_api-1.2.1.dist-info/top_level.txt
gt_sat_infile_api-1.2.1.dist-info/RECORD
