Metadata-Version: 2.1
Name: gt-sat-infile-api
Version: 1.2.1
Summary: GT SAT INFILE API
Home-page: https://gitlab.com/HomebrewSoft/l10n_gt/gt_sat_api
Author: HomebrewSoft
Author-email: moises@homebrewsoft.dev
License: MIT
Platform: UNKNOWN
